odoo10_addon_l10n_es_aeat_mod390-10.0.3.2.0-nspkg.pth
odoo/addons/l10n_es_aeat_mod390/README.rst
odoo/addons/l10n_es_aeat_mod390/__init__.py
odoo/addons/l10n_es_aeat_mod390/__manifest__.py
odoo/addons/l10n_es_aeat_mod390/data/aeat_export_mod390_2018_main_data.xml
odoo/addons/l10n_es_aeat_mod390/data/aeat_export_mod390_2018_sub01_data.xml
odoo/addons/l10n_es_aeat_mod390/data/aeat_export_mod390_2018_sub02_data.xml
odoo/addons/l10n_es_aeat_mod390/data/aeat_export_mod390_2018_sub03_data.xml
odoo/addons/l10n_es_aeat_mod390/data/aeat_export_mod390_2018_sub04_data.xml
odoo/addons/l10n_es_aeat_mod390/data/aeat_export_mod390_2018_sub05_data.xml
odoo/addons/l10n_es_aeat_mod390/data/aeat_export_mod390_2018_sub06_data.xml
odoo/addons/l10n_es_aeat_mod390/data/aeat_export_mod390_2018_sub07_data.xml
odoo/addons/l10n_es_aeat_mod390/data/aeat_export_mod390_2018_sub08_data.xml
odoo/addons/l10n_es_aeat_mod390/data/aeat_export_mod390_2019_main_data.xml
odoo/addons/l10n_es_aeat_mod390/data/aeat_export_mod390_2019_sub01_data.xml
odoo/addons/l10n_es_aeat_mod390/data/aeat_export_mod390_2019_sub02_data.xml
odoo/addons/l10n_es_aeat_mod390/data/aeat_export_mod390_2019_sub03_data.xml
odoo/addons/l10n_es_aeat_mod390/data/aeat_export_mod390_2019_sub04_data.xml
odoo/addons/l10n_es_aeat_mod390/data/aeat_export_mod390_2019_sub05_data.xml
odoo/addons/l10n_es_aeat_mod390/data/aeat_export_mod390_2019_sub06_data.xml
odoo/addons/l10n_es_aeat_mod390/data/aeat_export_mod390_2019_sub07_data.xml
odoo/addons/l10n_es_aeat_mod390/data/aeat_export_mod390_2019_sub08_data.xml
odoo/addons/l10n_es_aeat_mod390/data/aeat_export_mod390_main_data.xml
odoo/addons/l10n_es_aeat_mod390/data/aeat_export_mod390_sub01_data.xml
odoo/addons/l10n_es_aeat_mod390/data/aeat_export_mod390_sub02_data.xml
odoo/addons/l10n_es_aeat_mod390/data/aeat_export_mod390_sub03_data.xml
odoo/addons/l10n_es_aeat_mod390/data/aeat_export_mod390_sub04_data.xml
odoo/addons/l10n_es_aeat_mod390/data/aeat_export_mod390_sub05_data.xml
odoo10_addon_l10n_es_aeat_mod390-10.0.3.2.0.dist-info/METADATA
odoo10_addon_l10n_es_aeat_mod390-10.0.3.2.0.dist-info/WHEEL
odoo10_addon_l10n_es_aeat_mod390-10.0.3.2.0.dist-info/namespace_packages.txt
odoo10_addon_l10n_es_aeat_mod390-10.0.3.2.0.dist-info/top_level.txt
odoo10_addon_l10n_es_aeat_mod390-10.0.3.2.0.dist-info/RECORD
